plink/__init__.py
plink/app.py
plink/arrow.py
plink/canvasvg.py
plink/colors.py
plink/crossings.py
plink/dialog.py
plink/editor.py
plink/gui.py
plink/ipython_tools.py
plink/manager.py
plink/scaling.py
plink/smooth.py
plink/version.py
plink/vertex.py
plink/viewer.py
plink/__pycache__/__init__.cpython-312.pyc
plink/__pycache__/arrow.cpython-312.pyc
plink/__pycache__/canvasvg.cpython-312.pyc
plink/__pycache__/colors.cpython-312.pyc
plink/__pycache__/crossings.cpython-312.pyc
plink/__pycache__/dialog.cpython-312.pyc
plink/__pycache__/editor.cpython-312.pyc
plink/__pycache__/gui.cpython-312.pyc
plink/__pycache__/ipython_tools.cpython-312.pyc
plink/__pycache__/manager.cpython-312.pyc
plink/__pycache__/scaling.cpython-312.pyc
plink/__pycache__/smooth.cpython-312.pyc
plink/__pycache__/version.cpython-312.pyc
plink/__pycache__/vertex.cpython-312.pyc
plink/__pycache__/viewer.cpython-312.pyc
plink/doc/genindex.html
plink/doc/index.html
plink/doc/installing.html
plink/doc/objects.inv
plink/doc/plink.html
plink/doc/py-modindex.html
plink/doc/search.html
plink/doc/searchindex.js
plink/doc/_images/plink-action.png
plink/doc/_sources/index.rst.txt
plink/doc/_sources/installing.rst.txt
plink/doc/_sources/plink.rst.txt
plink/doc/_static/basic.css
plink/doc/_static/classic.css
plink/doc/_static/default.css
plink/doc/_static/doctools.js
plink/doc/_static/documentation_options.js
plink/doc/_static/file.png
plink/doc/_static/jquery-3.5.1.js
plink/doc/_static/jquery.js
plink/doc/_static/language_data.js
plink/doc/_static/minus.png
plink/doc/_static/plus.png
plink/doc/_static/pygments.css
plink/doc/_static/searchtools.js
plink/doc/_static/sidebar.js
plink/doc/_static/sphinx_highlight.js
plink/doc/_static/underscore-1.13.1.js
plink/doc/_static/underscore.js
plink-2.4.7.dist-info/METADATA
plink-2.4.7.dist-info/WHEEL
plink-2.4.7.dist-info/entry_points.txt
plink-2.4.7.dist-info/top_level.txt
plink-2.4.7.dist-info/RECORD
