Metadata-Version: 2.4
Name: plink
Version: 2.4.7
Summary: A full featured Tk-based knot and link editor
Home-page: https://github.com/3-manifolds/PLink
Author: Marc Culler and Nathan M. Dunfield
Author-email: culler@uic.edu, nathan@dunfield.info
License: GPLv2+
Keywords: knot,link,editor,SnapPy
Classifier: Development Status :: 5 - Production/Stable
Classifier: Intended Audience :: Science/Research
Classifier: Operating System :: OS Independent
Classifier: Programming Language :: Python
Classifier: Topic :: Scientific/Engineering :: Mathematics
